odoo/addons/partner_bank_code/README.rst
odoo/addons/partner_bank_code/__init__.py
odoo/addons/partner_bank_code/__manifest__.py
odoo/addons/partner_bank_code/i18n/fr.po
odoo/addons/partner_bank_code/i18n/hr.po
odoo/addons/partner_bank_code/i18n/it.po
odoo/addons/partner_bank_code/i18n/partner_bank_code.pot
odoo/addons/partner_bank_code/models/__init__.py
odoo/addons/partner_bank_code/models/res_bank.py
odoo/addons/partner_bank_code/readme/CONTRIBUTORS.md
odoo/addons/partner_bank_code/readme/DESCRIPTION.md
odoo/addons/partner_bank_code/readme/USAGE.md
odoo/addons/partner_bank_code/static/description/icon.png
odoo/addons/partner_bank_code/static/description/index.html
odoo/addons/partner_bank_code/tests/__init__.py
odoo/addons/partner_bank_code/tests/test_partner_bank_code.py
odoo/addons/partner_bank_code/views/res_bank.xml
odoo_addon_partner_bank_code-18.0.1.0.0.2.dist-info/METADATA
odoo_addon_partner_bank_code-18.0.1.0.0.2.dist-info/WHEEL
odoo_addon_partner_bank_code-18.0.1.0.0.2.dist-info/top_level.txt
odoo_addon_partner_bank_code-18.0.1.0.0.2.dist-info/RECORD
